{
"type": "FeatureCollection",
"name": "waypoints",
"crs": { "type": "name", "properties": { "name": "urn:ogc:def:crs:OGC:1.3:CRS84" } },
"features": [
{ "type": "Feature", "properties": { "ele": 67.0, "name": "0006673", "sym": "Waypoint" }, "geometry": { "type": "Point", "coordinates": [ 2.641809, 39.755266 ] } },
{ "type": "Feature", "properties": { "ele": 4.3, "name": "0006674", "sym": "Waypoint" }, "geometry": { "type": "Point", "coordinates": [ 2.655445, 39.769327 ] } },
{ "type": "Feature", "properties": { "ele": 309.3, "name": "0006675", "desc": "<p><br \/><h3>Nombre: Segmento: 1<\/h3><br \/>Hora Inicio: 10:12 30 may. 2021<br \/>Hora Fin: 15:06 30 may. 2021<br \/>Distancia recorrida: 15,8km (04:54)<br \/>Tiempo en movimiento: 03:13<br \/>Velocidad media: 3,23 km\/h<br \/>Vel. en Mov.: 4,9 km\/h<br \/>Velocidad Máxima: 57,38 km\/h<br \/>Altura Mínima: 4 m<br \/>Altura Máxima: 309 m<br \/>Velocidad Ascenso: 543 m\/h<br \/>Velocidad Descenso: 341,4 m\/h<br \/>Ganancia Altitud: 809 m<br \/>Pérdida Altitud: 580 m<br \/>Tiempo Ascenso: 01:29<br \/>Tiempo Descenso: 01:42<br \/><\/p>", "sym": "Waypoint" }, "geometry": { "type": "Point", "coordinates": [ 2.62798, 39.744047 ] } },
{ "type": "Feature", "properties": { "ele": 309.3, "name": "0006676", "desc": "<p><br \/><h3>Nombre: Segmento: 1<\/h3><br \/>Hora Inicio: 10:12 30 may. 2021<br \/>Hora Fin: 15:06 30 may. 2021<br \/>Distancia recorrida: 15,8km (04:54)<br \/>Tiempo en movimiento: 03:13<br \/>Velocidad media: 3,23 km\/h<br \/>Vel. en Mov.: 4,9 km\/h<br \/>Velocidad Máxima: 57,38 km\/h<br \/>Altura Mínima: 4 m<br \/>Altura Máxima: 309 m<br \/>Velocidad Ascenso: 543 m\/h<br \/>Velocidad Descenso: 341,4 m\/h<br \/>Ganancia Altitud: 809 m<br \/>Pérdida Altitud: 580 m<br \/>Tiempo Ascenso: 01:29<br \/>Tiempo Descenso: 01:42<br \/><\/p>", "sym": "Waypoint" }, "geometry": { "type": "Point", "coordinates": [ 2.62798, 39.744047 ] } }
]
}
